dimos_lcm/__init__.py
dimos_lcm/actionlib_msgs/GoalID.py
dimos_lcm/actionlib_msgs/GoalStatus.py
dimos_lcm/actionlib_msgs/GoalStatusArray.py
dimos_lcm/actionlib_msgs/__init__.py
dimos_lcm/builtin_interfaces/Duration.py
dimos_lcm/builtin_interfaces/Time.py
dimos_lcm/builtin_interfaces/__init__.py
dimos_lcm/diagnostic_msgs/DiagnosticArray.py
dimos_lcm/diagnostic_msgs/DiagnosticStatus.py
dimos_lcm/diagnostic_msgs/KeyValue.py
dimos_lcm/diagnostic_msgs/__init__.py
dimos_lcm/foxglove_bridge/__init__.py
dimos_lcm/foxglove_bridge/__main__.py
dimos_lcm/foxglove_bridge/bridge.py
dimos_lcm/foxglove_bridge/config.py
dimos_lcm/foxglove_bridge/message_converter.py
dimos_lcm/foxglove_bridge/message_processor.py
dimos_lcm/foxglove_bridge/models.py
dimos_lcm/foxglove_bridge/reverse_converter.py
dimos_lcm/foxglove_bridge/schema_generator.py
dimos_lcm/foxglove_bridge/server_listener.py
dimos_lcm/foxglove_bridge/test_bridge.py
dimos_lcm/foxglove_bridge/topic_discovery.py
dimos_lcm/foxglove_msgs/ArrowPrimitive.py
dimos_lcm/foxglove_msgs/CameraCalibration.py
dimos_lcm/foxglove_msgs/CircleAnnotation.py
dimos_lcm/foxglove_msgs/Color.py
dimos_lcm/foxglove_msgs/CompressedImage.py
dimos_lcm/foxglove_msgs/CompressedVideo.py
dimos_lcm/foxglove_msgs/CubePrimitive.py
dimos_lcm/foxglove_msgs/CylinderPrimitive.py
dimos_lcm/foxglove_msgs/FrameTransform.py
dimos_lcm/foxglove_msgs/FrameTransforms.py
dimos_lcm/foxglove_msgs/GeoJSON.py
dimos_lcm/foxglove_msgs/Grid.py
dimos_lcm/foxglove_msgs/ImageAnnotations.py
dimos_lcm/foxglove_msgs/KeyValuePair.py
dimos_lcm/foxglove_msgs/LaserScan.py
dimos_lcm/foxglove_msgs/LinePrimitive.py
dimos_lcm/foxglove_msgs/LocationFix.py
dimos_lcm/foxglove_msgs/Log.py
dimos_lcm/foxglove_msgs/ModelPrimitive.py
dimos_lcm/foxglove_msgs/PackedElementField.py
dimos_lcm/foxglove_msgs/Point2.py
dimos_lcm/foxglove_msgs/PointCloud.py
dimos_lcm/foxglove_msgs/PointsAnnotation.py
dimos_lcm/foxglove_msgs/PoseInFrame.py
dimos_lcm/foxglove_msgs/PosesInFrame.py
dimos_lcm-0.1.2.dist-info/METADATA
dimos_lcm-0.1.2.dist-info/WHEEL
dimos_lcm-0.1.2.dist-info/top_level.txt
dimos_lcm-0.1.2.dist-info/RECORD
