Metadata-Version: 2.4
Name: dimos_lcm
Version: 0.1.2
Summary: LCM-Foxglove bridge and message utilities for Dimensional Robotics
Author-email: Dimensional Team <build@dimensionalOS.com>
Project-URL: Homepage, https://github.com/dimensionalOS/dimos-lcm
Requires-Python: >=3.8
Requires-Dist: lcm
Requires-Dist: foxglove-websocket
Requires-Dist: numpy
